<?xml version="1.0" encoding="utf-8"?>
<TextDatabase xmlns:xsi="http://www.w3.org/2001/XMLSchema-instance" xsi:noNamespaceSchemaLocation="texts.xsd" Version="4.24.0">
  <Languages>
    <Language Id="GB" />
  </Languages>
  <Texts>
    <TextGroup Id="Group1">
      <Text Id="AlphaMode" Alignment="Center" TypographyId="Display">
        <Translation Language="GB">ABC</Translation>
      </Text>
      <Text Id="NumMode" Alignment="Center" TypographyId="Display">
        <Translation Language="GB">123</Translation>
      </Text>
      <Text Id="EnteredText" Alignment="Left" TypographyId="Display">
        <Translation Language="GB">&lt;placeholder&gt;</Translation>
      </Text>
    </TextGroup>
  </Texts>
  <Typographies>
    <Typography Id="Default" Font="verdana.ttf" Size="20" Bpp="4" IsVector="no" Direction="LTR" FallbackCharacter="?" />
    <Typography Id="Large" Font="verdana.ttf" Size="40" Bpp="4" IsVector="no" Direction="LTR" FallbackCharacter="?" />
    <Typography Id="Small" Font="verdana.ttf" Size="10" Bpp="4" IsVector="no" Direction="LTR" FallbackCharacter="?" />
    <Typography Id="Keyboard" Font="segoeui.ttf" Size="20" Bpp="4" IsVector="no" Direction="LTR" FallbackCharacter="?" WildcardCharacters="!”&quot;#*%&amp;()'$+-@_, .:;?/~±×÷•º`´{}©£€^®¥_=[]¡¢|\¿&gt;&lt;" WildcardCharacterRanges="a-z,A-Z,0-9" />
    <Typography Id="Display" Font="segoeui.ttf" Size="28" Bpp="4" IsVector="no" Direction="LTR" FallbackCharacter="?" WildcardCharacters="!”&quot;#*%&amp;()'$+-@_, .:;?/~±×÷•º`´{}©£€^®¥_=[]¡¢|\¿&gt;&lt;" WildcardCharacterRanges="a-z,A-Z,0-9" />
    <Typography Id="Mode" Font="segoeui.ttf" Size="24" Bpp="4" IsVector="no" Direction="LTR" />
  </Typographies>
</TextDatabase>
